sepya/__init__.py
sepya/misc.py
sepya/text.py
sepya/utils.py
sepya-0.0.3.dist-info/LICENSE
sepya-0.0.3.dist-info/METADATA
sepya-0.0.3.dist-info/WHEEL
sepya-0.0.3.dist-info/top_level.txt
sepya-0.0.3.dist-info/RECORD
