Metadata-Version: 2.1
Name: sepya
Version: 0.0.3
Summary: Utils to work with images.
Home-page: https://github.com/thorwhalen/newut/tree/master/sepya
Author: Thor Whalen
License: mit
Platform: any
License-File: LICENSE
